tweet_fetcher/__init__.py
tweet_fetcher/main.py
tweet_fetcher-1.0.dist-info/LICENSE
tweet_fetcher-1.0.dist-info/METADATA
tweet_fetcher-1.0.dist-info/WHEEL
tweet_fetcher-1.0.dist-info/top_level.txt
tweet_fetcher-1.0.dist-info/RECORD
