Metadata-Version: 2.1
Name: tweet_fetcher
Version: 1.0
Summary: Python library to retrieve tweet data without consuming the API or using your X account.
Home-page: https://github.com/DobleV55/tweet_fetcher
Author: DobleV55
Author-email: vilavalentin@gmail.com
Classifier: Programming Language :: Python :: 3
Classifier: License :: OSI Approved :: MIT License
Classifier: Operating System :: OS Independent
Requires-Python: >=3.6
License-File: LICENSE
Requires-Dist: requests
